tensorlm
