Metadata-Version: 1.1
Name: tensorlm
Version: 0.4.2
Summary: TensorFlow wrapper for deep neural text generation on character or word level with RNNs / LSTMs
Home-page: https://github.com/batzner/tensorlm
Author: Kilian Batzner
Author-email: tensorlm@kilians.net
License: MIT
Download-URL: https://github.com/batzner/tensorlm/archive/v0.4.2.tar.gz
Keywords: tensorflow,text,generation,language,model,rnn,lstm,deep,neural,char,word
Platform: UNKNOWN
Classifier: Development Status :: 3 - Alpha
Classifier: Intended Audience :: Developers
Classifier: Topic :: Scientific/Engineering :: Artificial Intelligence
Classifier: License :: OSI Approved :: MIT License
Classifier: Programming Language :: Python :: 3 :: Only
